pptx_shapes/__init__.py
pptx_shapes/presentation.py
pptx_shapes/units.py
pptx_shapes/charts/__init__.py
pptx_shapes/charts/bar/__init__.py
pptx_shapes/charts/bar/chart.py
pptx_shapes/charts/bar/config.py
pptx_shapes/charts/donut/__init__.py
pptx_shapes/charts/donut/chart.py
pptx_shapes/charts/donut/config.py
pptx_shapes/charts/line/__init__.py
pptx_shapes/charts/line/chart.py
pptx_shapes/charts/line/config.py
pptx_shapes/charts/scatter/__init__.py
pptx_shapes/charts/scatter/config.py
pptx_shapes/charts/scatter/plot.py
pptx_shapes/charts/scatter/point.py
pptx_shapes/entities/bbox.py
pptx_shapes/entities/namespace_helper.py
pptx_shapes/entities/slide.py
pptx_shapes/enums/__init__.py
pptx_shapes/enums/align.py
pptx_shapes/enums/arrow_size.py
pptx_shapes/enums/arrow_type.py
pptx_shapes/enums/line_dash.py
pptx_shapes/enums/vertical_align.py
pptx_shapes/shapes/__init__.py
pptx_shapes/shapes/arc.py
pptx_shapes/shapes/arch.py
pptx_shapes/shapes/arrow.py
pptx_shapes/shapes/ellipse.py
pptx_shapes/shapes/group.py
pptx_shapes/shapes/line.py
pptx_shapes/shapes/pie.py
pptx_shapes/shapes/polygon.py
pptx_shapes/shapes/polyline.py
pptx_shapes/shapes/rectangle.py
pptx_shapes/shapes/shape.py
pptx_shapes/shapes/textbox.py
pptx_shapes/style/__init__.py
pptx_shapes/style/arrowhead.py
pptx_shapes/style/fill_style.py
pptx_shapes/style/font_format.py
pptx_shapes/style/font_style.py
pptx_shapes/style/margin.py
pptx_shapes/style/stroke_style.py
pptx_shapes-0.3.1.dist-info/licenses/LICENSE
pptx_shapes-0.3.1.dist-info/METADATA
pptx_shapes-0.3.1.dist-info/WHEEL
pptx_shapes-0.3.1.dist-info/top_level.txt
pptx_shapes-0.3.1.dist-info/RECORD
