Metadata-Version: 2.4
Name: pptx-shapes
Version: 0.3.1
Summary: Python library for adding basic geometric shapes directly to PowerPoint (.pptx) slides by editing the XML structure.
Author-email: Andrew Perminov <dronperminov@gmail.com>
License: MIT License
Project-URL: Homepage, https://github.com/dronperminov/pptx-shapes
Project-URL: Repository, https://github.com/dronperminov/pptx-shapes
Project-URL: Documentation, https://pptx-shapes.readthedocs.io
Project-URL: Issues, https://github.com/dronperminov/pptx-shapes/issues
Project-URL: Changelog, https://github.com/dronperminov/pptx-shapes/blob/master/CHANGELOG.md
Keywords: powerpoint,pptx,xml,shape,geometry,line,rectangle,polygon,ellipse,text
Classifier: Intended Audience :: Developers
Classifier: Operating System :: OS Independent
Classifier: Programming Language :: Python :: 3
Classifier: Programming Language :: Python :: 3.8
Classifier: Programming Language :: Python :: 3.9
Classifier: Programming Language :: Python :: 3.10
Classifier: Programming Language :: Python :: 3.11
Classifier: Programming Language :: Python :: 3.12
Requires-Python: >=3.8
License-File: LICENSE
Requires-Dist: lxml>=3.1.0
Dynamic: license-file
